gpapi/__init__.py
gpapi/config.py
gpapi/device.properties
gpapi/googleplay.py
gpapi/googleplay_pb2.py
gpapi/utils.py
ak_gpapi-3.0.7.dist-info/LICENSE.md
ak_gpapi-3.0.7.dist-info/METADATA
ak_gpapi-3.0.7.dist-info/WHEEL
ak_gpapi-3.0.7.dist-info/top_level.txt
ak_gpapi-3.0.7.dist-info/RECORD
