Metadata-Version: 2.1
Name: ak-gpapi
Version: 3.0.7
Summary: Unofficial python api for google play
Home-page: https://github.com/appknox/googleplay-api
Author: appknox
Author-email: engineering@appknox.com
License: GPL3
License-File: LICENSE.md
Requires-Dist: cryptography <41
Requires-Dist: protobuf ==3.19.0
Requires-Dist: requests ==2.31.0
Requires-Dist: urllib3 <1.26.0
